setup.py
pyconfuserm/__init__.py
pyconfuserm.egg-info/PKG-INFO
pyconfuserm.egg-info/SOURCES.txt
pyconfuserm.egg-info/dependency_links.txt
pyconfuserm.egg-info/top_level.txt