Metadata-Version: 2.1
Name: pyconfuserm
Version: 0.0.1
Summary: This modules allows you to protect python scripts
Author: LOLEEEE
Author-email: LOLEEEE@gmail.com
License: MIT
Keywords: pyconfuserm
Classifier: Development Status :: 5 - Production/Stable
Classifier: Intended Audience :: Education
Classifier: Operating System :: Microsoft :: Windows :: Windows 10
Classifier: License :: OSI Approved :: MIT License
Classifier: Programming Language :: Python :: 3.9
